udprecorder/__init__.py
udprecorder/record_udp_stream.py
udprecorder/replay_udp_stream.py
udprecorder/utils.py
udprecorder-0.1.5.dist-info/entry_points.txt
udprecorder-0.1.5.dist-info/METADATA
udprecorder-0.1.5.dist-info/WHEEL
udprecorder-0.1.5.dist-info/RECORD
