Metadata-Version: 2.1
Name: udprecorder
Version: 0.1.5
Summary: Record and replay UDP streams
Author: Nicolas M.
Requires-Python: >=3.8,<4.0
Classifier: Programming Language :: Python :: 3
Classifier: Programming Language :: Python :: 3.8
Classifier: Programming Language :: Python :: 3.9
Classifier: Programming Language :: Python :: 3.10
Classifier: Programming Language :: Python :: 3.11
